firebase_scrypt/__init__.py
firebase_scrypt/_version.py
firebase_scrypt/firebasescrypt.py
firebase_scrypt/py.typed
firebase_scrypt-0.1.0.dist-info/LICENCE
firebase_scrypt-0.1.0.dist-info/METADATA
firebase_scrypt-0.1.0.dist-info/NOTICE
firebase_scrypt-0.1.0.dist-info/WHEEL
firebase_scrypt-0.1.0.dist-info/top_level.txt
firebase_scrypt-0.1.0.dist-info/RECORD
