Metadata-Version: 2.1
Name: firebase-scrypt
Version: 0.1.0
Summary: Python implementation of Firebase's scrypt password hashing algorithm.
Author-email: Jaakko Laurila <JaakkoL@users.noreply.github.com>, Nicholas Hairs <info@nicholashairs.com>
Maintainer-email: Nicholas Hairs <info@nicholashairs.com>
License: MIT License
Project-URL: homepage, https://github.com/nhairs/firebase-scrypt-python
Keywords: firebase,scrypt
Classifier: Development Status :: 5 - Production/Stable
Classifier: Programming Language :: Python :: 3 :: Only
Classifier: Programming Language :: Python :: 3.7
Classifier: Programming Language :: Python :: 3.8
Classifier: Programming Language :: Python :: 3.9
Classifier: Programming Language :: Python :: 3.10
Classifier: Programming Language :: Python :: 3.11
Classifier: Programming Language :: Python :: 3.12
Classifier: License :: OSI Approved :: MIT License
Classifier: Typing :: Typed
Classifier: Topic :: Security :: Cryptography
Classifier: Topic :: Software Development :: Libraries
Requires-Python: >=3.7
License-File: LICENCE
License-File: NOTICE
Requires-Dist: pycryptodome >=3.9
Provides-Extra: dev
Requires-Dist: validate-pyproject[all] ; extra == 'dev'
Requires-Dist: black ; extra == 'dev'
Requires-Dist: pylint ; extra == 'dev'
Requires-Dist: mypy ; extra == 'dev'
Requires-Dist: pytest ; extra == 'dev'
Requires-Dist: mkdocs ; extra == 'dev'
Requires-Dist: mkdocs-material >=8.5 ; extra == 'dev'
Requires-Dist: mkdocs-awesome-pages-plugin ; extra == 'dev'
Requires-Dist: mdx-truly-sane-lists ; extra == 'dev'
Requires-Dist: bpython ; extra == 'dev'
